pytest_respect/__init__.py
pytest_respect/_fakes.py
pytest_respect/plugin.py
pytest_respect/resources.py
pytest_respect/utils.py
pytest_respect/ext/__init__.py
pytest_respect/ext/jsonyx.py
pytest_respect-0.9.0.dist-info/METADATA
pytest_respect-0.9.0.dist-info/WHEEL
pytest_respect-0.9.0.dist-info/entry_points.txt
pytest_respect-0.9.0.dist-info/RECORD
