Metadata-Version: 2.4
Name: pytest-respect
Version: 0.9.0
Summary: Pytest plugin to load resource files relative to test code and to expect values to match them.
Project-URL: homepage, https://github.com/Ankeri/pytest-respect
Project-URL: issues, https://github.com/Ankeri/pytest-respect/issues
Author-email: Logi Ragnarsson <logi.ragnarsson@ankeri.is>
License-Expression: MIT
Classifier: Development Status :: 5 - Production/Stable
Classifier: Framework :: Pytest
Classifier: Intended Audience :: Developers
Classifier: License :: OSI Approved :: MIT License
Classifier: Operating System :: OS Independent
Classifier: Programming Language :: Python
Classifier: Programming Language :: Python :: 3 :: Only
Classifier: Programming Language :: Python :: 3.10
Classifier: Programming Language :: Python :: 3.11
Classifier: Programming Language :: Python :: 3.12
Classifier: Programming Language :: Python :: 3.13
Classifier: Programming Language :: Python :: Implementation :: CPython
Requires-Python: >=3.10
Requires-Dist: pytest>=8.0.0
Provides-Extra: jsonyx
Requires-Dist: jsonyx>=2.0.0; extra == 'jsonyx'
Provides-Extra: numpy
Requires-Dist: numpy>=2.0.0; extra == 'numpy'
Provides-Extra: pydantic
Requires-Dist: pydantic>=2.0.0; extra == 'pydantic'
